logfire_python.py
logfire_python-0.1.0.dist-info/METADATA
logfire_python-0.1.0.dist-info/WHEEL
logfire_python-0.1.0.dist-info/licenses/LICENSE
logfire_python-0.1.0.dist-info/RECORD
